rechi/__init__.py
rechi/rechi.py
rechi-1.0.0.dist-info/licenses/LICENSE
rechi-1.0.0.dist-info/METADATA
rechi-1.0.0.dist-info/WHEEL
rechi-1.0.0.dist-info/top_level.txt
rechi-1.0.0.dist-info/RECORD
