Metadata-Version: 2.4
Name: rechi
Version: 1.0.0
Summary: Regular Expression with CHain Iteration
Author-email: bazsalazas <ancsa.balazs@gmail.com>
License-Expression: GPL-3.0
Project-URL: Homepage, https://github.com/bazsalazas/rechi
Project-URL: Issues, https://github.com/bazsalazas/rechi/issues
Classifier: Programming Language :: Python :: 3
Classifier: Operating System :: OS Independent
Requires-Python: >=3.9
License-File: LICENSE
Dynamic: license-file
